phytoClassifier/__init__.py
phytoClassifier/level0.py
phytoClassifier/level1.py
phytoClassifier/level2.py
phytoClassifier/level3.py
phytoClassifier/level4.py
phytoClassifier/levelminus1.py
phytoClassifier/main.py
phytoClassifier/data/mclk.db
phytoClassifier-1.1.0.dist-info/LICENSE
phytoClassifier-1.1.0.dist-info/METADATA
phytoClassifier-1.1.0.dist-info/WHEEL
phytoClassifier-1.1.0.dist-info/top_level.txt
phytoClassifier-1.1.0.dist-info/RECORD
