Metadata-Version: 2.1
Name: phytoClassifier
Version: 1.1.0
Summary: A package for phytoChemicals classification
Home-page: https://github.com/jiangtao639/phytoClassifier
Author: TaoJiang
Author-email: silencetao@icloud.com
License: UNKNOWN
Project-URL: Author Github, https://github.com/jiangtao639/
Platform: UNKNOWN
Classifier: Programming Language :: Python :: 3
Classifier: License :: OSI Approved :: MIT License
Classifier: Operating System :: OS Independent
Requires-Python: >=3.8
License-File: LICENSE
